drf_builder/__init__.py
drf_builder/exceptions.py
drf_builder/middleware.py
drf_builder/routers.py
drf_builder/serializers.py
drf_builder/utils.py
drf_builder/views.py
drf_builder/viewsets.py
drf_builder-0.1.0.dist-info/licenses/LICENSE
tests/__init__.py
tests/conftest.py
tests/test_drf_builder.py
tests/urls.py
drf_builder-0.1.0.dist-info/METADATA
drf_builder-0.1.0.dist-info/WHEEL
drf_builder-0.1.0.dist-info/top_level.txt
drf_builder-0.1.0.dist-info/RECORD
