Metadata-Version: 2.4
Name: drf-builder
Version: 0.1.0
Summary: API dinâmica para Django que gera endpoints RESTful automaticamente para qualquer modelo
Home-page: https://github.com/campusinteligente/drf-builder
Author: Caio Ferreira, Eliandro de Souza, João Alves
Author-email: caio.tomaz@alunos.ifsuldeminas.edu.br
License: MIT
Project-URL: Bug Tracker, https://github.com/campusinteligente/drf-builder/issues
Keywords: django,api,rest,dynamic,drf,automatic,endpoints
Classifier: Development Status :: 4 - Beta
Classifier: Programming Language :: Python :: 3
Classifier: License :: OSI Approved :: MIT License
Classifier: Operating System :: OS Independent
Classifier: Framework :: Django
Classifier: Framework :: Django :: 3.0
Classifier: Framework :: Django :: 3.1
Classifier: Framework :: Django :: 3.2
Classifier: Framework :: Django :: 4.0
Classifier: Intended Audience :: Developers
Classifier: Topic :: Software Development :: Libraries :: Python Modules
Requires-Python: >=3.6
License-File: LICENSE
Requires-Dist: django>=3.0
Requires-Dist: djangorestframework>=3.11.0
Requires-Dist: django-filter>=21.1
Requires-Dist: djangorestframework-simplejwt>=5.2.2
Dynamic: author
Dynamic: author-email
Dynamic: classifier
Dynamic: description
Dynamic: description-content-type
Dynamic: home-page
Dynamic: keywords
Dynamic: license-file
Dynamic: project-url
Dynamic: requires-dist
Dynamic: requires-python
Dynamic: summary
